PoTKential/__init__.py
PoTKential/abstractClasses.py
PoTKential/clustering.py
PoTKential/matrix.py
PoTKential/sgd.py
PoTKential/testClustering.py
PoTKential/testMatrix.py
PoTKential/testSGD.py
PoTKential/testVector.py
PoTKential/vector.py
PoTKential-0.0.1.dist-info/LICENSE
PoTKential-0.0.1.dist-info/METADATA
PoTKential-0.0.1.dist-info/WHEEL
PoTKential-0.0.1.dist-info/top_level.txt
PoTKential-0.0.1.dist-info/RECORD
