Metadata-Version: 2.1
Name: PoTKential
Version: 0.0.1
Summary: UNKNOWN
Home-page: UNKNOWN
Author: Jacob Barrow
Author-email: jacob.h.barrow@gmail.com
License: MIT
Platform: UNKNOWN
Classifier: License :: OSI Approved :: MIT License
Classifier: Programming Language :: Python
Classifier: Programming Language :: Python :: 3
License-File: LICENSE
Requires-Dist: numpy
Requires-Dist: sklearn
Requires-Dist: sympy
